MANIFEST.in
README.rst
setup.py
crr_labels/__init__.py
crr_labels/__version__.py
crr_labels/fantom.json
crr_labels/fantom.py
crr_labels/roadmap.json
crr_labels/roadmap.py
crr_labels.egg-info/PKG-INFO
crr_labels.egg-info/SOURCES.txt
crr_labels.egg-info/dependency_links.txt
crr_labels.egg-info/requires.txt
crr_labels.egg-info/top_level.txt
crr_labels/utils/__init__.py
crr_labels/utils/center_window.py
crr_labels/utils/filter_required_cell_lines.py
crr_labels/utils/load_bed.py
crr_labels/utils/normalize_bed_file.py
crr_labels/utils/normalize_cell_lines.py
crr_labels/utils/validate_common_parameters.py