Metadata-Version: 2.1
Name: crr-labels
Version: 1.1.1
Summary: Python package wrapping over FANTOM and Roadmap labels for cis regulatory regions.
Home-page: https://github.com/LucaCappelletti94/crr_labels
Author: Luca Cappelletti
Author-email: cappelletti.luca94@gmail.com
License: MIT
Platform: UNKNOWN
Classifier: Development Status :: 3 - Alpha
Classifier: License :: OSI Approved :: MIT License
Classifier: Programming Language :: Python :: 3
Provides-Extra: test
